CHANGES.txt
LICENSE.txt
MANIFEST.in
README.md
setup.py
pywizard_extra_modules/__init__.py
pywizard_extra_modules/mysql.py
pywizard_extra_modules/nginx.py
pywizard_extra_modules/nodejs.py
pywizard_extra_modules/phpfpm.py
pywizard_extra_modules/ssl.py
pywizard_extra_modules/stunnel.py
pywizard_extra_modules/utils.py
pywizard_extra_modules/varnish.py
pywizard_extra_modules.egg-info/PKG-INFO
pywizard_extra_modules.egg-info/SOURCES.txt
pywizard_extra_modules.egg-info/dependency_links.txt
pywizard_extra_modules.egg-info/requires.txt
pywizard_extra_modules.egg-info/top_level.txt
pywizard_extra_modules/templates/default.vcl
pywizard_extra_modules/templates/fake_ssl_script.sh
pywizard_extra_modules/templates/fastcgi_params
pywizard_extra_modules/templates/index.php
pywizard_extra_modules/templates/install-app.sh
pywizard_extra_modules/templates/install-nodejs.sh
pywizard_extra_modules/templates/install_nginx.sh
pywizard_extra_modules/templates/my.cnf
pywizard_extra_modules/templates/netiapteek-live.vcl
pywizard_extra_modules/templates/nginx-init-centos
pywizard_extra_modules/templates/nginx-init-ubuntu
pywizard_extra_modules/templates/nginx-main.conf
pywizard_extra_modules/templates/nginx.conf
pywizard_extra_modules/templates/nodejs-na-live.conf
pywizard_extra_modules/templates/php-fpm.conf
pywizard_extra_modules/templates/sites.vcl
pywizard_extra_modules/templates/stunnel.conf
pywizard_extra_modules/templates/varnish-default