Metadata-Version: 1.0
Name: pywizard-extra-modules
Version: 0.1.15
Summary: Pack of modules for Pywizard
Home-page: UNKNOWN
Author: Alex Rudakov
Author-email: ribozz@gmail.com
License: MIT
Platform: UNKNOWN
